{
	"ImportPath": "github.com/mauidude/deduper",
	"GoVersion": "go1.4",
	"Packages": [
		"./..."
	],
	"Deps": [
		{
			"ImportPath": "code.google.com/p/gogoprotobuf/proto",
			"Rev": "5c5c9e5ec21508be656c201ec53c68cd882d36fb"
		},
		{
			"ImportPath": "code.google.com/p/goprotobuf/proto",
			"Comment": "go.r60-163",
			"Rev": "9352842ae63ee1d7e74e074ce7bb10370c4b6b9e"
		},
		{
			"ImportPath": "github.com/codegangsta/negroni",
			"Comment": "v0.1-55-g1dd3ab0",
			"Rev": "1dd3ab0ff59e13f5b73dcbf70703710aebe50d2f"
		},
		{
			"ImportPath": "github.com/deckarep/golang-set",
			"Comment": "v1-26-gef32fa3",
			"Rev": "ef32fa3046d9f249d399f98ebaf9be944430fd1d"
		},
		{
			"ImportPath": "github.com/goraft/raft",
			"Rev": "0555185d6b9d51059afda8f299442777b422cc87"
		},
		{
			"ImportPath": "github.com/gorilla/context",
			"Rev": "14f550f51af52180c2eefed15e5fd18d63c0a64a"
		},
		{
			"ImportPath": "github.com/gorilla/mux",
			"Rev": "14cafe28513321476c73967a5a4f3454b6129c46"
		},
		{
			"ImportPath": "github.com/stretchr/testify/assert",
			"Rev": "2eaa4b48b8954bf871229043b8064ca156a542a5"
		},
		{
			"ImportPath": "github.com/stretchr/testify/require",
			"Rev": "2eaa4b48b8954bf871229043b8064ca156a542a5"
		}
	]
}
